{"nodes": [{"id": "readme_create_react_app", "label": "Create React App", "file_type": "concept", "source_file": "README.md", "source_location": null, "source_url": "https://github.com/facebook/create-react-app", "captured_at": null, "author": null, "contributor": null}, {"id": "readme_react_documentation", "label": "React Documentation", "file_type": "document", "source_file": "README.md", "source_location": null, "source_url": "https://reactjs.org/", "captured_at": null, "author": null, "contributor": null}], "edges": [{"source": "readme_create_react_app", "target": "readme_react_documentation", "relation": "references", "confidence": "EXTRACTED", "confidence_score": 1.0, "source_file": "README.md", "source_location": null, "weight": 1.0}, {"source": "readme_create_react_app", "target": "agents_project_tech_stack", "relation": "conceptually_related_to", "confidence": "AMBIGUOUS", "confidence_score": 0.6, "source_file": "README.md", "source_location": null, "weight": 1.0}], "hyperedges": []}